Ehsan/src/Sequential_Multiplier/src/controller.sv
/*********************************************************************************
  +  Author      : Muhammad Ehsan
  +  Date        : 27-7-2024
  +  Description : Implementation of sequential multiplier using booth algorithm.
*********************************************************************************/

module controller (

//======================= Declearing Input And Outputs =======================//

    input     logic     clk,
    input     logic     rst,
    input     logic     Q0_bit,
    input     logic     Q_1_bit,
    input     logic     counter_signal,
    input     logic     start_bit,

    output    logic     mux0_sel,
    output    logic     mux1_sel,
    output    logic     mux2_sel,
    output    logic     alu_ctrl,
    output    logic     counter_en,
    output    logic     ready_bit,
    output    logic     clear_bit
);
//============================= State Machine ================================//

    logic c_state, n_state;
    parameter idle = 0, multiplication = 1;

    always_ff @(posedge clk or negedge rst) begin
        if (!rst) begin
            c_state <= idle;
        end
        else begin
            c_state <= n_state;
        end
    end

    always_comb begin
        case (c_state)
            idle: begin
                mux2_sel = 0;
                if (start_bit == 0) begin
                    clear_bit = 1;
                    ready_bit = 0;
                    mux0_sel = 0;
                    n_state = idle;
                end

                else if (start_bit == 1) begin
                    clear_bit = 0;
                    ready_bit = 0;
                    mux0_sel = 0;
                    mux1_sel = 0;
                    counter_en = 1;
                    n_state = multiplication;
                end
            end

            multiplication: begin
                if (counter_signal == 1) begin
                    mux2_sel = 1;
                    ready_bit = 1;
                    clear_bit = 1;
                    counter_en = 0;
                    n_state = idle;
                end

                else if (counter_signal == 0) begin
                    ready_bit = 0;
                    clear_bit = 0;
                    mux0_sel = 1;
                    counter_en = 1;
                    n_state = multiplication;
                    if (Q0_bit == 1'b0 && Q_1_bit == 1'b0) begin
                        mux1_sel = 1'b0;
                    end else if (Q0_bit == 1'b1 && Q_1_bit == 1'b1) begin
                        mux1_sel = 1'b0;
                    end else if (Q0_bit == 1'b1 && Q_1_bit == 1'b0) begin
                        mux1_sel = 1'b1;
                        alu_ctrl = 1'b1;
                    end else if (Q0_bit == 1'b0 && Q_1_bit == 1'b1) begin
                        mux1_sel = 1'b1;
                        alu_ctrl = 1'b0;
                    end
                end
            end
        endcase
    end
endmodule

Ehsan/src/Sequential_Multiplier/src/data_path.sv
/*********************************************************************************
  +  Author      : Muhammad Ehsan
  +  Date        : 27-7-2024
  +  Description : Implementation of sequential multiplier using booth algorithm.
*********************************************************************************/

module data_path (

//======================= Declearing Input And Outputs =======================//

    input    logic                         clk,
    input    logic                         rst,
    input    logic   [MUL_WIDTH-1:0]       multiplicand,
    input    logic   [MUL_WIDTH-1:0]       multiplier,
    input    logic                         clear_bit,
    input    logic                         mux0_sel,
    input    logic                         mux1_sel,
    input    logic                         mux2_sel,
    input    logic                         counter_en,
    input    logic                         alu_ctrl,

    output   logic   [(2*MUL_WIDTH)-1:0]   product,
    output   logic                         counter_signal,
    output   logic                         Q_1_bit,
    output   logic                         Q0_bit
);
//======================= Declearing Internal Signals ========================//

    logic                            Q_0_bit, Q_1__bit;
    logic   [$clog2(MUL_WIDTH)+1:0]  counter;
    logic   [MUL_WIDTH-1:0]          Q, M, A, mux0_out, mux1_out, alu_out;
    logic   [(2*MUL_WIDTH)-1:0]      combined_shift_A_Q;

//===================== Q(0) And Q(-1) Bit Of Multiplier =====================//

assign Q_1_bit = Q_1__bit;
assign Q0_bit = Q[0]; 

//================================== Mux 0 ===================================//

assign mux0_out = (mux0_sel) ? combined_shift_A_Q[MUL_WIDTH-1:0] : multiplier;

//================================== Mux 1 ===================================//

assign mux1_out = (mux1_sel) ? alu_out : A;

//================================== Mux 2 ===================================//

assign product  = (mux2_sel) ? combined_shift_A_Q : 0;

//=================================== ALU ====================================//

always_comb begin 
    case (alu_ctrl)
        0:
            alu_out = A + M;
        1: 
            alu_out = A - M;
    endcase
end

//============================== Right Shifting ==============================//

assign combined_shift_A_Q = {mux1_out[MUL_WIDTH-1],mux1_out[MUL_WIDTH-1:0],Q[MUL_WIDTH-1:1]};

//=============================== Comparator =================================//

assign counter_signal = (counter == MUL_WIDTH) ? 1 : 0;

//================================ Registers =================================//

always_ff @(posedge clk or negedge rst) begin
    if (!rst) begin
        Q <= 0;
        M <= 0;
        A <= 0;
        Q_1__bit <= 0;
        counter <= 0;
    end

    if (clear_bit) begin
        Q <= 0;
        M <= 0;
        A <= 0;
        Q_1__bit <= 0;
        counter <= 0;
    end

    else begin          
        Q <= mux0_out;
        M <= multiplicand;
        A <=  combined_shift_A_Q[(2*MUL_WIDTH)-1:MUL_WIDTH];
        Q_1__bit <=  Q[0];
        
        if(counter_en == 1) begin                    
            counter <= counter + 1;
        end
    end
end

endmodule

Ehsan/src/Sequential_Multiplier/src/sequential_multiplier_top.sv
/*********************************************************************************
  +  Author      : Muhammad Ehsan
  +  Date        : 27-7-2024
  +  Description : Implementation of sequential multiplier using booth algorithm.
*********************************************************************************/

module sequential_multiplier (

//======================= Declearing Input And Outputs =======================//

    input   logic                       clk,
    input   logic                       rst,
    input   logic  [MUL_WIDTH-1:0]      multiplicand,
    input   logic  [MUL_WIDTH-1:0]      multiplier,
    input   logic                       start_bit,
    output  logic                       ready_bit,
    output  logic  [(2*MUL_WIDTH)-1:0]  product
);

//======================= Declearing Internal Signals ========================//

    logic  mux0_sel, mux1_sel, mux2_sel, counter_en, counter_signal;
    logic  Q_1_bit, Q0_bit, clear_bit, alu_ctrl;

//=========================== Module Instantiation ===========================//

    data_path data_path(
        .clk(clk),
        .rst(rst),
        .clear_bit(clear_bit),
        .multiplier(multiplier),
        .multiplicand(multiplicand),
        .product(product),
        .Q0_bit(Q0_bit),
        .Q_1_bit(Q_1_bit),
        .counter_signal(counter_signal),
        .mux0_sel(mux0_sel),
        .mux1_sel(mux1_sel),
        .mux2_sel(mux2_sel),
        .counter_en(counter_en),
        .alu_ctrl(alu_ctrl)
    );

//=========================== Module Instantiation ===========================//

    controller ctrl_unit(
        .clk(clk),
        .rst(rst),
        .clear_bit(clear_bit),
        .ready_bit(ready_bit),
        .start_bit(start_bit),
        .Q0_bit(Q0_bit),
        .Q_1_bit(Q_1_bit),
        .counter_signal(counter_signal),
        .mux0_sel(mux0_sel),
        .mux1_sel(mux1_sel),
        .mux2_sel(mux2_sel),
        .counter_en(counter_en),
        .alu_ctrl(alu_ctrl)
    );

endmodule

Ehsan/src/Sequential_Multiplier/test/tb_sequential_multiplier.sv
/*********************************************************************************
  +  Author      : Muhammad Ehsan
  +  Date        : 27-7-2024
  +  Description : Implementation of sequential multiplier using booth algorithm.
*********************************************************************************/

parameter MUL_WIDTH = 16;

module tb;

    int Passed;                                         //No. of tests passes
    int Failed;                                         //No. of tests fails
    int test_cases = 1000;                             //No. of tests
    logic signed   [(2*MUL_WIDTH)-1:0]   exp_product;   //Expected Product

//=================== Declearing Input And Outputs For UUT ===================//

    logic                                clk;
    logic                                rst;
    logic signed   [MUL_WIDTH-1:0]       multiplicand;
    logic signed   [MUL_WIDTH-1:0]       multiplier;
    logic signed   [(2*MUL_WIDTH)-1:0]   product;
    logic                                start_bit;
    logic                                ready_bit;

//=========================== Module Instantiation ===========================//

    sequential_multiplier #(.MUL_WIDTH(MUL_WIDTH)) uut (
        .clk(clk),
        .rst(rst),
        .start_bit(start_bit),
        .ready_bit(ready_bit),
        .multiplicand(multiplicand),
        .multiplier(multiplier),
        .product(product)
    );
//============================= Clock Generation =============================//

    initial begin
        clk = 1;
        forever #5 clk = ~clk;
    end

//=============================== RESET Circuit ==============================//

    task reset_circuit;
        rst = 0;
        #5;
        rst = 1;
    endtask

//============================== Driving Inputs ==============================//

    task drive_inputs (input logic signed [MUL_WIDTH-1:0] in_1, input logic signed [MUL_WIDTH-1:0] in_2);
        begin
            multiplicand = in_1;
            multiplier = in_2;
            start_bit = 1;
            @(posedge clk);
            start_bit = 0;
        end
    endtask

//============================ Monitoring Outputs ============================//

    task monitor_outputs;
        begin
            exp_product = multiplicand * multiplier;
            while (ready_bit == 0) begin
                @(posedge clk);            
            end;
            if(exp_product != product)begin
                Failed++;
                $display("Fail");
                $display("multiplicand = %0d, multiplier = %0d, product = %0d, expected= %0d", multiplicand, multiplier, product,exp_product);
            end
            else
            begin
                Passed++;
                $display("Pass");
            end
        end
    endtask

//================================== Testing =================================//

    initial begin
        reset_circuit;

        // Direct Test
        drive_inputs ($random % ((2^MUL_WIDTH)-1),$random % ((2^MUL_WIDTH)-1)); 
        monitor_outputs;

        //Random Testing
        for(int i=0;i<test_cases-1;i++) begin 
            drive_inputs ($random % ((2^MUL_WIDTH)-1),$random % ((2^MUL_WIDTH)-1)); 
            monitor_outputs;
        end

        @(posedge clk);
        $display("No. of test = %0d, Passed = %0d, Failed = %0d", test_cases,Passed, Failed);
        $finish;
    end

//=========================== Generating Waveform ============================//

    initial begin
        $dumpfile("waveform.vcd");
        $dumpvars(0);
    end

endmodule

Ehsan/src/Sequential_Multiplier/waveform.vcd
$date
	Sat Aug 10 14:09:54 2024
$end
$version
	Icarus Verilog
$end
$timescale
	1s
$end
$scope module tb $end
$var wire 1 ! ready_bit $end
$var wire 32 " product [31:0] $end
$var reg 1 # clk $end
$var reg 32 $ exp_product [31:0] $end
$var reg 16 % multiplicand [15:0] $end
$var reg 16 & multiplier [15:0] $end
$var reg 1 ' rst $end
$var reg 1 ( start_bit $end
$var integer 32 ) Failed [31:0] $end
$var integer 32 * Passed [31:0] $end
$var integer 32 + test_cases [31:0] $end
$scope module uut $end
$var wire 1 # clk $end
$var wire 16 , multiplicand [15:0] $end
$var wire 16 - multiplier [15:0] $end
$var wire 1 ' rst $end
$var wire 1 ( start_bit $end
$var wire 1 ! ready_bit $end
$var wire 32 . product [31:0] $end
$var wire 1 / mux2_sel $end
$var wire 1 0 mux1_sel $end
$var wire 1 1 mux0_sel $end
$var wire 1 2 counter_signal $end
$var wire 1 3 counter_en $end
$var wire 1 4 clear_bit $end
$var wire 1 5 alu_ctrl $end
$var wire 1 6 Q_1_bit $end
$var wire 1 7 Q0_bit $end
$scope module ctrl_unit $end
$var wire 1 # clk $end
$var wire 1 ' rst $end
$var wire 1 ( start_bit $end
$var wire 1 2 counter_signal $end
$var wire 1 6 Q_1_bit $end
$var wire 1 7 Q0_bit $end
$var reg 1 5 alu_ctrl $end
$var reg 1 8 c_state $end
$var reg 1 4 clear_bit $end
$var reg 1 3 counter_en $end
$var reg 1 1 mux0_sel $end
$var reg 1 0 mux1_sel $end
$var reg 1 / mux2_sel $end
$var reg 1 9 n_state $end
$var reg 1 ! ready_bit $end
$upscope $end
$scope module data_path $end
$var wire 1 6 Q_1_bit $end
$var wire 1 5 alu_ctrl $end
$var wire 1 4 clear_bit $end
$var wire 1 # clk $end
$var wire 1 3 counter_en $end
$var wire 16 : multiplicand [15:0] $end
$var wire 16 ; multiplier [15:0] $end
$var wire 1 1 mux0_sel $end
$var wire 1 0 mux1_sel $end
$var wire 1 / mux2_sel $end
$var wire 1 ' rst $end
$var wire 32 < product [31:0] $end
$var wire 16 = mux1_out [15:0] $end
$var wire 16 > mux0_out [15:0] $end
$var wire 1 2 counter_signal $end
$var wire 32 ? combined_shift_A_Q [31:0] $end
$var wire 1 7 Q0_bit $end
$var reg 16 @ A [15:0] $end
$var reg 16 A M [15:0] $end
$var reg 16 B Q [15:0] $end
$var reg 1 C Q_1__bit $end
$var reg 16 D alu_out [15:0] $end
$var reg 6 E counter [5:0] $end
$upscope $end
$upscope $end
$scope begin $ivl_for_loop0 $end
$var integer 32 F i [31:0] $end
$upscope $end
$scope task drive_inputs $end
$var reg 16 G in_1 [15:0] $end
$var reg 16 H in_2 [15:0] $end
$upscope $end
$scope task monitor_outputs $end
$upscope $end
$scope task reset_circuit $end
$upscope $end
$upscope $end
$enddefinitions $end
#0
$dumpvars
bx H
bx G
b0 F
b0 E
bx D
xC
bx B
bx A
bx @
bx ?
bx >
bx =
b0 <
bx ;
bx :
x9
08
x7
x6
x5
x4
x3
02
x1
x0
0/
b0 .
bx -
bx ,
b1111101000 +
b0 *
b0 )
x(
0'
bx &
bx %
bx $
1#
b0 "
x!
$end
#5
b1111111111110110 >
19
13
00
01
0!
04
1(
b1111111111110110 &
b1111111111110110 -
b1111111111110110 ;
b1001 %
b1001 ,
b1001 :
b1111111111110110 H
b1001 G
1'
0#
#10
bx111111111111011 >
11
07
bx111111111111011 ?
18
b1 E
b1001 A
b1111111111110110 B
19
04
b11111111111111111111111110100110 $
0(
1#
#15
0#
#20
bx11111111111101 >
15
10
17
bx11111111111101 ?
b10 E
06
0C
bx111111111111011 B
1#
#25
0#
#30
bx1111111111110 >
00
bx1111111111110 ?
b11 E
16
1C
bx11111111111101 B
1#
#35
0#
#40
bx111111111111 >
05
10
07
bx111111111111 ?
b100 E
bx1111111111110 B
1#
#45
0#
#50
bx11111111111 >
15
17
bx11111111111 ?
b101 E
06
0C
bx111111111111 B
1#
#55
0#
#60
bx1111111111 >
00
bx1111111111 ?
b110 E
16
1C
bx11111111111 B
1#
#65
0#
#70
bx111111111 >
bx111111111 ?
b111 E
bx1111111111 B
1#
#75
0#
#80
bx11111111 >
bx11111111 ?
b1000 E
bx111111111 B
1#
#85
0#
#90
bx1111111 >
bx1111111 ?
b1001 E
bx11111111 B
1#
#95
0#
#100
bx111111 >
bx111111 ?
b1010 E
bx1111111 B
1#
#105
0#
#110
bx11111 >
bx11111 ?
b1011 E
bx111111 B
1#
#115
0#
#120
bx1111 >
bx1111 ?
b1100 E
bx11111 B
1#
#125
0#
#130
bx111 >
bx111 ?
b1101 E
bx1111 B
1#
#135
0#
#140
bx11 >
bx11 ?
b1110 E
bx111 B
1#
#145
0#
#150
bx1 >
bx1 ?
b1111 E
bx11 B
1#
#155
0#
#160
bx "
bx .
bx <
09
03
14
1!
1/
bx >
12
bx ?
b10000 E
bx1 B
1#
#165
0#
#170
02
b1111111111110101 >
b0 "
b0 .
b0 <
19
13
01
0!
04
0/
b0 =
b0 D
07
b0 ?
08
b0 E
06
0C
b0 @
b0 A
b0 B
1(
b1111111111110101 &
b1111111111110101 -
b1111111111110101 ;
b1111111111111001 %
b1111111111111001 ,
b1111111111111001 :
b1111111111110101 H
b1111111111111001 G
b1 *
1#
#175
0#
#180
b111 =
10
b1111111111111010 >
17
b111111111111111010 ?
b111 D
11
b1 E
b1111111111111001 A
b1111111111110101 B
18
19
04
b1001101 $
0(
1#
#185
0#
#190
b111111111111101 >
b1111111111111100 =
05
b1111111111111100 D
07
b11111111111111100111111111111101 ?
b10 E
16
1C
b11 @
b1111111111111010 B
1#
#195
0#
#200
b1011111111111110 >
b101 =
15
b101 D
17
b101011111111111110 ?
b11 E
06
0C
b1111111111111110 @
b111111111111101 B
1#
#205
0#
#210
b1101111111111111 >
b1111111111111011 =
05
b1111111111111011 D
07
b11111111111111011101111111111111 ?
b100 E
16
1C
b10 @
b1011111111111110 B
1#
#215
0#
#220
b110111111111111 >
b100 =
15
b100 D
17
b100110111111111111 ?
b101 E
06
0C
b1111111111111101 @
b1101111111111111 B
1#
#225
0#
#230
b11011111111111 >
b10 =
00
b1001 D
b10011011111111111 ?
b110 E
16
1C
b10 @
b110111111111111 B
1#
#235
0#
#240
b1001101111111111 >
b1000 D
b1 =
b1001101111111111 ?
b111 E
b1 @
b11011111111111 B
1#
#245
0#
#250
b100110111111111 >
b111 D
b0 =
b100110111111111 ?
b1000 E
b0 @
b1001101111111111 B
1#
#255
0#
#260
b10011011111111 >
b10011011111111 ?
b1001 E
b100110111111111 B
1#
#265
0#
#270
b1001101111111 >
b1001101111111 ?
b1010 E
b10011011111111 B
1#
#275
0#
#280
b100110111111 >
b100110111111 ?
b1011 E
b1001101111111 B
1#
#285
0#
#290
b10011011111 >
b10011011111 ?
b1100 E
b100110111111 B
1#
#295
0#
#300
b1001101111 >
b1001101111 ?
b1101 E
b10011011111 B
1#
#305
0#
#310
b100110111 >
b100110111 ?
b1110 E
b1001101111 B
1#
#315
0#
#320
b10011011 >
b10011011 ?
b1111 E
b100110111 B
1#
#325
0#
#330
b1001101 "
b1001101 .
b1001101 <
09
03
14
1!
1/
b1001101 >
12
b1001101 ?
b10000 E
b10011011 B
1#
#335
0#
#340
02
b1001 >
b0 "
b0 .
b0 <
07
b0 ?
b0 D
19
13
01
0!
04
0/
b0 E
06
0C
b0 A
b0 B
08
1(
b1001 &
b1001 -
b1001 ;
b100 %
b100 ,
b100 :
b1001 H
b100 G
b1 F
b10 *
1#
#345
0#
#350
b1111111111111100 =
b100 >
10
11
b1111111111111100 D
17
b11111111111111100000000000000100 ?
18
b1 E
b100 A
b1001 B
19
04
b100100 $
0(
1#
#355
0#
#360
b10 >
b10 =
05
b10 D
07
b10000000000000010 ?
b10 E
16
1C
b1111111111111110 @
b100 B
1#
#365
0#
#370
b1000000000000001 >
b1 =
00
b101 D
b1000000000000001 ?
b11 E
06
0C
b1 @
b10 B
1#
#375
0#
#380
b100000000000000 >
15
10
b1111111111111100 D
b1111111111111100 =
17
b11111111111111100100000000000000 ?
b100 E
b0 @
b1000000000000001 B
1#
#385
0#
#390
b10000000000000 >
b10 =
05
b10 D
07
b10010000000000000 ?
b101 E
16
1C
b1111111111111110 @
b100000000000000 B
1#
#395
0#
#400
b1001000000000000 >
b1 =
00
b101 D
b1001000000000000 ?
b110 E
06
0C
b1 @
b10000000000000 B
1#
#405
0#
#410
b100100000000000 >
b100 D
b0 =
b100100000000000 ?
b111 E
b0 @
b1001000000000000 B
1#
#415
0#
#420
b10010000000000 >
b10010000000000 ?
b1000 E
b100100000000000 B
1#
#425
0#
#430
b1001000000000 >
b1001000000000 ?
b1001 E
b10010000000000 B
1#
#435
0#
#440
b100100000000 >
b100100000000 ?
b1010 E
b1001000000000 B
1#
#445
0#
#450
b10010000000 >
b10010000000 ?
b1011 E
b100100000000 B
1#
#455
0#
#460
b1001000000 >
b1001000000 ?
b1100 E
b10010000000 B
1#
#465
0#
#470
b100100000 >
b100100000 ?
b1101 E
b1001000000 B
1#
#475
0#
#480
b10010000 >
b10010000 ?
b1110 E
b100100000 B
1#
#485
0#
#490
b1001000 >
b1001000 ?
b1111 E
b10010000 B
1#
#495
0#
#500
b100100 "
b100100 .
b100100 <
09
03
14
1!
1/
b100100 >
12
b100100 ?
b10000 E
b1001000 B
1#
#505
0#
#510
b1111111111110001 >
02
b0 "
b0 .
b0 <
19
13
01
0!
04
0/
b0 D
b0 ?
08
b0 E
b0 A
b0 B
1(
b1111111111110001 &
b1111111111110001 -
b1111111111110001 ;
b1111111111111000 %
b1111111111111000 ,
b1111111111111000 :
b1111111111110001 H
b1111111111111000 G
b10 F
b11 *
1#
#515
0#
#520
b1000 =
15
10
b111111111111000 >
17
b1000111111111111000 ?
b1000 D
11
b1 E
b1111111111111000 A
b1111111111110001 B
18
19
04
b1111000 $
0(
1#
#525
0#
#530
b11111111111100 >
b1111111111111100 =
05
b1111111111111100 D
07
b11111111111111100011111111111100 ?
b10 E
16
1C
b100 @
b111111111111000 B
1#
#535
0#
#540
b1111111111110 >
b1111111111111110 =
00
b1111111111110110 D
b11111111111111110001111111111110 ?
b11 E
06
0C
b1111111111111110 @
b11111111111100 B
1#
#545
0#
#550
b1000111111111111 >
b1111111111110111 D
b1111111111111111 =
b11111111111111111000111111111111 ?
b100 E
b1111111111111111 @
b1111111111110 B
1#
#555
0#
#560
b111 =
b1100011111111111 >
b111 D
15
10
17
b111100011111111111 ?
b101 E
b1000111111111111 B
1#
#565
0#
#570
b1110001111111111 >
b11 =
00
b1011 D
b11110001111111111 ?
b110 E
16
1C
b11 @
b1100011111111111 B
1#
#575
0#
#580
b1111000111111111 >
b1001 D
b1 =
b1111000111111111 ?
b111 E
b1 @
b1110001111111111 B
1#
#585
0#
#590
b111100011111111 >
b1000 D
b0 =
b111100011111111 ?
b1000 E
b0 @
b1111000111111111 B
1#
#595
0#
#600
b11110001111111 >
b11110001111111 ?
b1001 E
b111100011111111 B
1#
#605
0#
#610
b1111000111111 >
b1111000111111 ?
b1010 E
b11110001111111 B
1#
#615
0#
#620
b111100011111 >
b111100011111 ?
b1011 E
b1111000111111 B
1#
#625
0#
#630
b11110001111 >
b11110001111 ?
b1100 E
b111100011111 B
1#
#635
0#
#640
b1111000111 >
b1111000111 ?
b1101 E
b11110001111 B
1#
#645
0#
#650
b111100011 >
b111100011 ?
b1110 E
b1111000111 B
1#
#655
0#
#660
b11110001 >
b11110001 ?
b1111 E
b111100011 B
1#
#665
0#
#670
b1111000 "
b1111000 .
b1111000 <
09
03
14
1!
1/
b1111000 >
12
b1111000 ?
b10000 E
b11110001 B
1#
#675
0#
#680
02
b1110 >
b0 "
b0 .
b0 <
07
b0 ?
b0 D
19
13
01
0!
04
0/
b0 E
06
0C
b0 A
b0 B
08
1(
b1110 &
b1110 -
b1110 ;
b1100 %
b1100 ,
b1100 :
b1110 H
b1100 G
b11 F
b100 *
1#
#685
0#
#690
b111 >
11
b1111111111110100 D
b111 ?
18
b1 E
b1100 A
b1110 B
19
04
b10101000 $
0(
1#
#695
0#
#700
b1111111111110100 =
b11 >
10
17
b11111111111110100000000000000011 ?
b10 E
b111 B
1#
#705
0#
#710
b1 >
b1111111111111010 =
00
b1111111111101110 D
b11111111111111010000000000000001 ?
b11 E
16
1C
b1111111111111010 @
b11 B
1#
#715
0#
#720
b1000000000000000 >
b1111111111110001 D
b1111111111111101 =
b11111111111111101000000000000000 ?
b100 E
b1111111111111101 @
b1 B
1#
#725
0#
#730
b100000000000000 >
05
10
b1010 D
b1010 =
07
b1010100000000000000 ?
b101 E
b1111111111111110 @
b1000000000000000 B
1#
#735
0#
#740
b1010000000000000 >
b101 =
00
b10001 D
b101010000000000000 ?
b110 E
06
0C
b101 @
b100000000000000 B
1#
#745
0#
#750
b101000000000000 >
b1110 D
b10 =
b10101000000000000 ?
b111 E
b10 @
b1010000000000000 B
1#
#755
0#
#760
b1010100000000000 >
b1101 D
b1 =
b1010100000000000 ?
b1000 E
b1 @
b101000000000000 B
1#
#765
0#
#770
b101010000000000 >
b1100 D
b0 =
b101010000000000 ?
b1001 E
b0 @
b1010100000000000 B
1#
#775
0#
#780
b10101000000000 >
b10101000000000 ?
b1010 E
b101010000000000 B
1#
#785
0#
#790
b1010100000000 >
b1010100000000 ?
b1011 E
b10101000000000 B
1#
#795
0#
#800
b101010000000 >
b101010000000 ?
b1100 E
b1010100000000 B
1#
#805
0#
#810
b10101000000 >
b10101000000 ?
b1101 E
b101010000000 B
1#
#815
0#
#820
b1010100000 >
b1010100000 ?
b1110 E
b10101000000 B
1#
#825
0#
#830
b101010000 >
b101010000 ?
b1111 E
b1010100000 B
1#
#835
0#
#840
b10101000 "
b10101000 .
b10101000 <
09
03
14
1!
1/
b10101000 >
12
b10101000 ?
b10000 E
b101010000 B
1#
#845
0#
#850
b1100 >
02
b0 "
b0 .
b0 <
19
13
01
0!
04
0/
b0 D
b0 ?
08
b0 E
b0 A
b0 B
1(
b1100 &
b1100 -
b1100 ;
b1011 %
b1011 ,
b1011 :
b1100 H
b1011 G
b100 F
b101 *
1#
#855
0#
#860
b110 >
b110 ?
b1011 D
11
b1 E
b1011 A
b1100 B
18
19
04
b10000100 $
0(
1#
#865
0#
#870
b11 >
b11 ?
b10 E
b110 B
1#
#875
0#
#880
b1111111111110101 =
b1000000000000001 >
b1111111111110101 D
15
10
17
b11111111111110101000000000000001 ?
b11 E
b11 B
1#
#885
0#
#890
b100000000000000 >
b1111111111111010 =
00
b1111111111101111 D
b11111111111111010100000000000000 ?
b100 E
16
1C
b1111111111111010 @
b1000000000000001 B
1#
#895
0#
#900
b10000000000000 >
05
10
b1000 D
b1000 =
07
b1000010000000000000 ?
b101 E
b1111111111111101 @
b100000000000000 B
1#
#905
0#
#910
b1000000000000 >
b100 =
00
b1111 D
b100001000000000000 ?
b110 E
06
0C
b100 @
b10000000000000 B
1#
#915
0#
#920
b100000000000 >
b1101 D
b10 =
b10000100000000000 ?
b111 E
b10 @
b1000000000000 B
1#
#925
0#
#930
b1000010000000000 >
b1100 D
b1 =
b1000010000000000 ?
b1000 E
b1 @
b100000000000 B
1#
#935
0#
#940
b100001000000000 >
b1011 D
b0 =
b100001000000000 ?
b1001 E
b0 @
b1000010000000000 B
1#
#945
0#
#950
b10000100000000 >
b10000100000000 ?
b1010 E
b100001000000000 B
1#
#955
0#
#960
b1000010000000 >
b1000010000000 ?
b1011 E
b10000100000000 B
1#
#965
0#
#970
b100001000000 >
b100001000000 ?
b1100 E
b1000010000000 B
1#
#975
0#
#980
b10000100000 >
b10000100000 ?
b1101 E
b100001000000 B
1#
#985
0#
#990
b1000010000 >
b1000010000 ?
b1110 E
b10000100000 B
1#
#995
0#
#1000
b100001000 >
b100001000 ?
b1111 E
b1000010000 B
1#
#1005
0#
#1010
b10000100 "
b10000100 .
b10000100 <
09
03
14
1!
1/
b10000100 >
12
b10000100 ?
b10000 E
b100001000 B
1#
#1015
0#
#1020
02
b1001 >
b0 "
b0 .
b0 <
b0 ?
b0 D
19
13
01
0!
04
0/
b0 E
b0 A
b0 B
08
1(
b1001 &
b1001 -
b1001 ;
b1000 %
b1000 ,
b1000 :
b1001 H
b1000 G
b101 F
b110 *
1#
#1025
0#
#1030
b1111111111111000 =
b100 >
15
10
11
b1111111111111000 D
17
b11111111111111000000000000000100 ?
18
b1 E
b1000 A
b1001 B
19
04
b1001000 $
0(
1#
#1035
0#
#1040
b10 >
b100 =
05
b100 D
07
b100000000000000010 ?
b10 E
16
1C
b1111111111111100 @
b100 B
1#
#1045
0#
#1050
b1 >
b10 =
00
b1010 D
b10000000000000001 ?
b11 E
06
0C
b10 @
b10 B
1#
#1055
0#
#1060
b1000000000000000 >
15
10
b1111111111111001 D
b1111111111111001 =
17
b11111111111111001000000000000000 ?
b100 E
b1 @
b1 B
1#
#1065
0#
#1070
b100000000000000 >
b100 =
05
b100 D
07
b100100000000000000 ?
b101 E
16
1C
b1111111111111100 @
b1000000000000000 B
1#
#1075
0#
#1080
b10000000000000 >
b10 =
00
b1010 D
b10010000000000000 ?
b110 E
06
0C
b10 @
b100000000000000 B
1#
#1085
0#
#1090
b1001000000000000 >
b1001 D
b1 =
b1001000000000000 ?
b111 E
b1 @
b10000000000000 B
1#
#1095
0#
#1100
b100100000000000 >
b1000 D
b0 =
b100100000000000 ?
b1000 E
b0 @
b1001000000000000 B
1#
#1105
0#
#1110
b10010000000000 >
b10010000000000 ?
b1001 E
b100100000000000 B
1#
#1115
0#
#1120
b1001000000000 >
b1001000000000 ?
b1010 E
b10010000000000 B
1#
#1125
0#
#1130
b100100000000 >
b100100000000 ?
b1011 E
b1001000000000 B
1#
#1135
0#
#1140
b10010000000 >
b10010000000 ?
b1100 E
b100100000000 B
1#
#1145
0#
#1150
b1001000000 >
b1001000000 ?
b1101 E
b10010000000 B
1#
#1155
0#
#1160
b100100000 >
b100100000 ?
b1110 E
b1001000000 B
1#
#1165
0#
#1170
b10010000 >
b10010000 ?
b1111 E
b100100000 B
1#
#1175
0#
#1180
b1001000 "
b1001000 .
b1001000 <
09
03
14
1!
1/
b1001000 >
12
b1001000 ?
b10000 E
b10010000 B
1#
#1185
0#
#1190
b1111111111110100 >
02
b0 "
b0 .
b0 <
19
13
01
0!
04
0/
b0 D
b0 ?
08
b0 E
b0 A
b0 B
1(
b1111111111110100 &
b1111111111110100 -
b1111111111110100 ;
b1001 %
b1001 ,
b1001 :
b1111111111110100 H
b1001 G
b110 F
b111 *
1#
#1195
0#
#1200
b111111111111010 >
b111111111111010 ?
b1001 D
11
b1 E
b1001 A
b1111111111110100 B
18
19
04
b11111111111111111111111110010100 $
0(
1#
#1205
0#
#1210
b11111111111101 >
b11111111111101 ?
b10 E
b111111111111010 B
1#
#1215
0#
#1220
b1111111111110111 =
b1001111111111110 >
b1111111111110111 D
15
10
17
b11111111111110111001111111111110 ?
b11 E
b11111111111101 B
1#
#1225
0#
#1230
b100111111111111 >
b100 =
05
b100 D
07
b100100111111111111 ?
b100 E
16
1C
b1111111111111011 @
b1001111111111110 B
1#
#1235
0#
#1240
b1010011111111111 >
b1111111111111001 =
15
b1111111111111001 D
17
b11111111111111001010011111111111 ?
b101 E
06
0C
b10 @
b100111111111111 B
1#
#1245
0#
#1250
b101001111111111 >
b1111111111111100 =
00
b1111111111110011 D
b11111111111111100101001111111111 ?
b110 E
16
1C
b1111111111111100 @
b1010011111111111 B
1#
#1255
0#
#1260
b10100111111111 >
b1111111111110101 D
b1111111111111110 =
b11111111111111110010100111111111 ?
b111 E
b1111111111111110 @
b101001111111111 B
1#
#1265
0#
#1270
b1001010011111111 >
b1111111111110110 D
b1111111111111111 =
b11111111111111111001010011111111 ?
b1000 E
b1111111111111111 @
b10100111111111 B
1#
#1275
0#
#1280
b1100101001111111 >
b11111111111111111100101001111111 ?
b1001 E
b1001010011111111 B
1#
#1285
0#
#1290
b1110010100111111 >
b11111111111111111110010100111111 ?
b1010 E
b1100101001111111 B
1#
#1295
0#
#1300
b1111001010011111 >
b11111111111111111111001010011111 ?
b1011 E
b1110010100111111 B
1#
#1305
0#
#1310
b1111100101001111 >
b11111111111111111111100101001111 ?
b1100 E
b1111001010011111 B
1#
#1315
0#
#1320
b1111110010100111 >
b11111111111111111111110010100111 ?
b1101 E
b1111100101001111 B
1#
#1325
0#
#1330
b1111111001010011 >
b11111111111111111111111001010011 ?
b1110 E
b1111110010100111 B
1#
#1335
0#
#1340
b1111111100101001 >
b11111111111111111111111100101001 ?
b1111 E
b1111111001010011 B
1#
#1345
0#
#1350
b11111111111111111111111110010100 "
b11111111111111111111111110010100 .
b11111111111111111111111110010100 <
09
03
14
1!
1/
b1111111110010100 >
12
b11111111111111111111111110010100 ?
b10000 E
b1111111100101001 B
1#
#1355
0#
