Ibrahim/src/sequential_logic/pop_quiz/src/pop_quiz.sv
module d_flip_flop (
    input logic  clk,
    input logic  reset,
    input logic  d,
    output logic q
);
    always_ff @(posedge clk or posedge reset) begin
        if (reset)
            q <= #1 0;
        else
            q <= #1 d;
    end
endmodule

module pop_quiz (
    input logic  clk,
    input logic  reset,
    input logic  d_in,  // Input to the first flip-flop
    output logic a     // Output from the third flip-flop
);
    logic x, y, b;

    // Instantiate the first D flip-flop
    d_flip_flop ff1 (
        .clk(clk),
        .reset(reset),
        .d(d_in),
        .q(x)
    );

    // Compute Y as the NOT of X
    assign y = ~x;

    // Instantiate the second D flip-flop
    d_flip_flop ff2 (
        .clk(clk),
        .reset(reset),
        .d(y),
        .q(b)
    );

    // Instantiate the third D flip-flop
    d_flip_flop ff3 (
        .clk(clk),
        .reset(reset),
        .d(b),
        .q(a)
    );
endmodule

Ibrahim/src/sequential_logic/pop_quiz/test/pop_quiz_tb.sv
module pop_quiz_tb;

    // Parameters
    parameter CLK_PERIOD = 10; // Clock perioD in time units

    // Testbench signals
    logic clk;
    logic reset;
    logic D;
    logic A;

    // Instantiate the pop_quiz moDule
    pop_quiz uut (
        .clk(clk),
        .reset(reset),
        .d_in(D),
        .a(A)
    );

    // Clock generation
    initial begin
        clk = 0;
        forever #(CLK_PERIOD / 2) clk = ~clk; // Clock perioD of 10 time units
    end

    // Task to assert anD De-assert reset
    task assert_reset;
        begin
            @(posedge clk);
            reset = 1;
            @(posedge clk);
            reset = 0;
        end
    endtask

    // Test sequence
    initial begin
        // Initialize signals
        reset = 0;
        D = 0;

        // Apply reset
        assert_reset;

        // Apply test vectors
        @(posedge clk);
        D = 1; // Set D to 1
        repeat(2)@(posedge clk);
        @(posedge clk);
        D = 0; // Set D to 0
        @(posedge clk);
        @(posedge clk);
        D = 1; // Set D to 1
        @(posedge clk);
        @(posedge clk);
        D = 0; // Set D to 0

        // Finish simulation after some time
        repeat (10) @(posedge clk);
        $finish;
    end

    // Monitor outputs
    initial begin
        $display("Time\tReset\tD\tA");
        $monitor("%0t\t%b\t%b\t%b", $time, reset, D, A);
    end

    // Generate waveform Dump for visualization
    initial begin
        $dumpfile("pop_quiz/test/pop_quiz.vcd");
        $dumpvars(0, pop_quiz_tb);
    end

endmodule

Ibrahim/src/sequential_logic/pop_quiz.vcD
$date
	Thu Jul 25 11:35:13 2024
$end
$version
	Icarus Verilog
$end
$timescale
	1s
$end
$scope module pop_quiz_tb $end
$var wire 1 ! A $end
$var reg 1 " D $end
$var reg 1 # clk $end
$var reg 1 $ reset $end
$scope module uut $end
$var wire 1 # clk $end
$var wire 1 " d_in $end
$var wire 1 $ reset $end
$var wire 1 % y $end
$var wire 1 & x $end
$var wire 1 ' b $end
$var wire 1 ! a $end
$scope module ff1 $end
$var wire 1 # clk $end
$var wire 1 " d $end
$var wire 1 $ reset $end
$var reg 1 & q $end
$upscope $end
$scope module ff2 $end
$var wire 1 # clk $end
$var wire 1 % d $end
$var wire 1 $ reset $end
$var reg 1 ' q $end
$upscope $end
$scope module ff3 $end
$var wire 1 # clk $end
$var wire 1 ' d $end
$var wire 1 $ reset $end
$var reg 1 ! q $end
$upscope $end
$upscope $end
$scope task assert_reset $end
$upscope $end
$upscope $end
$enddefinitions $end
#0
$dumpvars
x'
x&
x%
0$
0#
0"
x!
$end
#5
1$
1#
#6
1%
0&
0'
0!
#10
0#
#15
0$
1#
#16
1'
#20
0#
#25
1"
1#
#26
0%
1&
1!
#30
0#
#35
1#
#36
0'
#40
0#
#45
1#
#46
0!
#50
0#
#55
0"
1#
#56
1%
0&
#60
0#
#65
1#
#66
1'
#70
0#
#75
1"
1#
#76
0%
1!
1&
#80
0#
#85
1#
#86
0'
#90
0#
#95
0"
1#
#96
1%
0!
0&
#100
0#
#105
1#
#106
1'
#110
0#
#115
1#
#116
1!
