Hira/Verilog/Sequential_counter/sequential_counter.sv
module counter(
    input   logic           clk,    // Clock signal
    input   logic           rst,    // Reset signal
    input   logic      bit_number, 
    output  logic      system_output
);

logic [3:0] bit_count;

localparam S0=2'b00;  
localparam S3=2'b11;
localparam S2=2'b10;


logic [1:0] CS,NS;

always_comb begin
    case(CS)
        S0: begin
            if (bit_number==1)begin
                NS=S3;
                end
            else begin
                NS=S2;
            end 
            end
        S3: begin
            if (bit_number==0)begin
                NS=S2;
            end
            else begin
                NS=S3;
            end
            end
        S2: begin
            if (bit_number==0)begin
                NS=S2;
            end
            else begin
                NS=S2;
            end
        end
        default: 
            NS=S0;
    endcase
    
end



always_comb begin
    case(CS)
        S0: begin
            if (bit_number==1)begin
                system_output = 1'b0; // addition with 1
                end
            else begin
                system_output = 1'b1; // addition with 1
            end 
            end
        S3: begin
            if (bit_number==0)begin
                system_output = 1'b1; // addition with previous carry
            end
            else begin
                system_output = 1'b0; // addition with previous carry
            end
            end
        S2: begin
            if (bit_number==0)begin
                system_output = 1'b0; // addition with previous carry
            end
            else begin
                system_output = 1'b1; // addition with previous carry
            end
        end
        default: 
            system_output = 1'b1;
    endcase
    
end




// Sequential logic to update state and carry
always_ff @(posedge clk or posedge rst) begin 
    if (rst | bit_count==4'd3 ) begin
        CS<=S0;
        bit_count <= 0;
    end else begin
        CS<=NS;
        bit_count <= bit_count + 1;
    end
end

endmodule

Hira/Verilog/Sequential_counter/tb_sequential_counter.sv
module tb_Sequential_counter();
    logic       clk;
    logic       rst;
    logic  bit_number; 
    logic  state;

    counter dut (
        .clk(clk),
        .rst(rst),    
        .bit_number(bit_number), 
        .system_output(state)
    );

    // Clock generation
    initial begin
        clk = 0;
        forever #5 clk = ~clk; // 10 time units clock period
    end

    initial begin
        rst = 1;

        @(posedge clk) 
        rst = 0;
        //for 2
        bit_number = 1'b0;
        @(posedge clk) 
        bit_number = 1'b1;
        @(posedge clk) 
        bit_number = 1'b0;
        @(posedge clk) 
        bit_number = 1'b0;
        @(posedge clk) 

        //for 3
        bit_number = 1'b1;
        @(posedge clk) 
        bit_number = 1'b1;
        @(posedge clk) 
        bit_number = 1'b0;
        @(posedge clk) 
        bit_number = 1'b0;
        @(posedge clk) 


         //for 4
        bit_number = 1'b0;
        @(posedge clk) 
        bit_number = 1'b0;
        @(posedge clk) 
        bit_number = 1'b1;
        @(posedge clk) 
        bit_number = 1'b0;
        @(posedge clk) 


         //for 5
        bit_number = 1'b1;
        @(posedge clk) 
        bit_number = 1'b0;
        @(posedge clk) 
        bit_number = 1'b1;
        @(posedge clk) 
        bit_number = 1'b0;
        @(posedge clk) 

         //for 6
        bit_number = 1'b0;
        @(posedge clk) 
        bit_number = 1'b1;
        @(posedge clk) 
        bit_number = 1'b1;
        @(posedge clk) 
        bit_number = 1'b0;
        @(posedge clk) 


        $monitor("At time %t, bit_numbe%d ,state = %d", $time, bit_number ,state);

        $finish;
    end
    

    initial begin
        $dumpfile("counter.vcd");
        $dumpvars(0, dut);
    end


endmodule

Hira/Verilog/Sequential_counter/counter.vcd
$date
	Mon Jul 29 10:07:46 2024
$end
$version
	QuestaSim Version 2021.1
$end
$timescale
	1ns
$end

$scope module tb_Sequential_counter $end

$scope module dut $end
$var parameter 2 ! S0 $end
$var parameter 2 " S3 $end
$var parameter 2 # S2 $end
$var wire 1 $ clk $end
$var wire 1 % rst $end
$var wire 1 & bit_number $end
$var reg 1 ' system_output $end
$var reg 4 ( bit_count [3:0] $end
$var reg 2 ) CS [1:0] $end
$var reg 2 * NS [1:0] $end
$upscope $end
$upscope $end
$enddefinitions $end
#0
$dumpvars
1'
b0 (
b0 )
b10 *
b0 !
b11 "
b10 #
x&
1%
0$
$end
#5
1$
0%
0&
#10
0$
#15
1$
1&
b11 *
0'
b10 )
b1 (
b10 *
1'
#20
0$
#25
1$
0&
0'
b10 (
#30
0$
#35
1$
b11 (
#40
0$
#45
1$
1&
1'
b0 )
b0 (
b11 *
0'
#50
0$
#55
1$
b11 )
b1 (
#60
0$
#65
1$
0&
b10 *
1'
b10 (
#70
0$
#75
1$
b10 )
b11 (
0'
#80
0$
#85
1$
b0 )
b0 (
1'
#90
0$
#95
1$
b10 )
b1 (
0'
#100
0$
#105
1$
1&
1'
b10 (
#110
0$
#115
1$
0&
0'
b11 (
#120
0$
#125
1$
1&
1'
b0 )
b0 (
b11 *
0'
#130
0$
#135
1$
0&
b10 *
1'
b11 )
b1 (
#140
0$
#145
1$
1&
b11 *
0'
b10 )
b10 (
b10 *
1'
#150
0$
#155
1$
0&
0'
b11 (
#160
0$
#165
1$
b0 )
b0 (
1'
#170
0$
#175
1$
1&
b11 *
0'
b10 )
b1 (
b10 *
1'
#180
0$
#185
1$
b10 (
#190
0$
#195
1$
0&
0'
b11 (
