Moazzam/src/cocotb/restoring_division/restoring_division_con.sv
module restoring_division_con
#(
    parameter BITS = 16
)
(
    input logic clk,rst,
    input logic valid_src, 
    input logic stop, 
    output logic load_en, 
    output logic update_en, 
    output logic counter_en, 
    output logic ans_sel,
    output logic valid_des,
    output logic clear
);

logic c_state, n_state;
parameter S0    =   0;
parameter S1    =   1;

always_ff @(posedge clk or negedge rst) begin
    if(!rst)  c_state <= S0;
    else      c_state <= n_state;  
end

always_comb 
begin
    case (c_state)
        S0:
        begin
            if(valid_src) n_state = S1;
            else          n_state = S0;
        end

        S1:
        begin
            if(stop)    n_state = S0;
            else        n_state = S1;
        end
    endcase
end


always_comb 
begin
    case (c_state)
        S0:
        begin
            counter_en = 1'b0;
            clear = 1'b1;
        
            if(valid_src) 
            begin 
                load_en = 1'b1;
            end
            else
            begin 
                load_en = 1'b0;
            end
        end

        S1:
        begin
            load_en = '0;
            counter_en = 1'b1;
            clear = '0;
            if(stop) 
            begin 
                valid_des = 1'b1;
                update_en = 1'b0;
                ans_sel   = 1'b1;
            end
            else
            begin 
                valid_des = 1'b0;
                update_en = 1'b1;
                ans_sel   = 1'b0;
            end
        end
    endcase
end

endmodule

Moazzam/src/cocotb/restoring_division/src/restoring_division.sv
module restoring_division  
(
    input logic clk,rst,

    input logic [16-1:0] divisor, //M -- md
    input logic [16-1:0] dividend, //Q -- qd
    input logic valid_src,

    output logic [16-1:0] reminder,
    output logic [16-1:0] quotient,
    output logic valid_des
);

logic [16:0] ac;
logic [16:0] md;
logic [16-1:0] qd;
logic load_en;
logic sel;
logic [(2*16):0] ac_qd;
logic [16:0] ac_s;
logic [16-1:0] qd_s;

logic [16:0] ac_p;

logic [16:0] ac_in;
logic [16-1:0] qd_in;
logic update_en;

logic [$clog2(16):0] counter;    
logic counter_en;
logic clear;

logic stop;


restoring_division_con CON (clk,rst,valid_src, stop, load_en, update_en, counter_en, ans_sel, valid_des,clear);

//assert (divisor == 0) else $fatal("Maths error! no number is divided by zero.");


always_ff @(posedge clk or negedge rst) 
begin
    if(!rst )
    begin
        ac <= '0;
        md <= '0;
        qd <= '0;
    end
    else 
    begin
        if (load_en) 
        begin
            ac <= '0;
            md <= {1'b0,divisor};
            qd <= dividend;
        end
        else if (update_en) 
        begin
            ac <= ac_in;
            qd <= qd_in;
        end
        else
        begin
            ac <= ac;
            md <= md;
            qd <= qd;
        end
    end

    if (!rst || clear)               counter <= '0;
    else if (counter_en)    counter <= counter + 1;
    else                    counter <= counter;
end

always_comb begin
    stop  = (counter == 16);
    ac_qd = ({ac, qd}) << 1;
    ac_s  =  ac_qd[32: 16];
    qd_s  =  ac_qd[16-1 : 0];

    ac_p  = ac_s - md;

    sel = ac_p[16];
    case (sel)
        1'b0: 
        begin
            ac_in = ac_p;
            qd_in = qd_s | 16'h0001;
        end

        1'b1: 
        begin
            ac_in = ac_s;
            qd_in = qd_s & 16'hfffe;
        end

    endcase

    quotient = ans_sel? qd : '0;
    reminder = ans_sel? ac[16-1:0] : '0;
end


endmodule

Moazzam/src/cocotb/restoring_division/test/tb_cocotb.sv
module tb_py_cocotb;

// Inputs
logic [15:0] dividend;
logic [15:0] divisor;
logic clk;
logic rst;
logic valid_src;


// Outputs
logic valid_des;
logic [15:0] quotient;
logic [15:0] reminder;


restoring_division uut (
    .dividend(dividend),
    .divisor(divisor),
    .clk(clk),
    .rst(rst),
    .valid_src(valid_src),
    .valid_des(valid_des),
    .quotient(quotient),
    .reminder(reminder)
);

    // Dump file for waveform
    initial begin
        $dumpfile("tb_cocotb.vcd");
        $dumpvars(0,tb_py_cocotb);
    end

endmodule

Moazzam/src/cocotb/restoring_division/test/tb_cocotb.vcd
$date
	Fri Aug  9 02:01:04 2024
$end
$version
	Icarus Verilog
$end
$timescale
	1ps
$end
$scope module tb_py_cocotb $end
$var wire 1 ! valid_des $end
$var wire 16 " reminder [15:0] $end
$var wire 16 # quotient [15:0] $end
$var reg 1 $ clk $end
$var reg 16 % dividend [15:0] $end
$var reg 16 & divisor [15:0] $end
$var reg 1 ' rst $end
$var reg 1 ( valid_src $end
$scope module uut $end
$var wire 1 $ clk $end
$var wire 16 ) dividend [15:0] $end
$var wire 16 * divisor [15:0] $end
$var wire 1 ' rst $end
$var wire 1 ( valid_src $end
$var wire 1 ! valid_des $end
$var wire 1 + update_en $end
$var wire 1 , load_en $end
$var wire 1 - counter_en $end
$var wire 1 . clear $end
$var wire 1 / ans_sel $end
$var reg 17 0 ac [16:0] $end
$var reg 17 1 ac_in [16:0] $end
$var reg 17 2 ac_p [16:0] $end
$var reg 33 3 ac_qd [32:0] $end
$var reg 17 4 ac_s [16:0] $end
$var reg 5 5 counter [4:0] $end
$var reg 17 6 md [16:0] $end
$var reg 16 7 qd [15:0] $end
$var reg 16 8 qd_in [15:0] $end
$var reg 16 9 qd_s [15:0] $end
$var reg 16 : quotient [15:0] $end
$var reg 16 ; reminder [15:0] $end
$var reg 1 < sel $end
$var reg 1 = stop $end
$scope module CON $end
$var wire 1 $ clk $end
$var wire 1 ' rst $end
$var wire 1 = stop $end
$var wire 1 ( valid_src $end
$var reg 1 / ans_sel $end
$var reg 1 > c_state $end
$var reg 1 . clear $end
$var reg 1 - counter_en $end
$var reg 1 , load_en $end
$var reg 1 ? n_state $end
$var reg 1 + update_en $end
$var reg 1 ! valid_des $end
$upscope $end
$upscope $end
$upscope $end
$enddefinitions $end
#0
$dumpvars
0?
0>
0=
0<
b0 ;
b0 :
b0 9
b1 8
b0 7
b0 6
b0 5
b0 4
b0 3
b0 2
b0 1
b0 0
x/
1.
0-
0,
x+
b0 *
b0 )
0(
0'
b0 &
b0 %
1$
b0 #
b0 "
x!
$end
#5000
0$
#10000
1'
1$
#15000
0$
#20000
1?
1,
b1010 &
b1010 *
1(
1$
#25000
0$
#30000
0(
b0 8
1<
b11111111111110110 2
0/
1+
0!
0.
1-
0,
b1010 6
1>
1$
#35000
0$
#40000
b1 5
1$
#45000
0$
#50000
b10 5
1$
#55000
0$
#60000
b11 5
1$
#65000
0$
#70000
b100 5
1$
#75000
0$
#80000
b101 5
1$
#85000
0$
#90000
b110 5
1$
#95000
0$
#100000
b111 5
1$
#105000
0$
#110000
b1000 5
1$
#115000
0$
#120000
b1001 5
1$
#125000
0$
#130000
b1010 5
1$
#135000
0$
#140000
b1011 5
1$
#145000
0$
#150000
b1100 5
1$
#155000
0$
#160000
b1101 5
1$
#165000
0$
#170000
b1110 5
1$
#175000
0$
#180000
b1111 5
1$
#185000
0$
#190000
0?
1/
0+
1!
1=
b10000 5
1$
#195000
0$
#200000
1.
0-
0=
0>
b10001 5
1$
#205000
0$
#210000
b0 5
1$
#215000
0$
#220000
1?
1,
b1111011 &
b1111011 *
b1111011 %
b1111011 )
1(
1$
#225000
0$
#230000
0(
b11110110 8
b11111111110000101 2
b11110110 9
b11110110 3
0/
1+
0!
0.
1-
0,
b1111011 7
b1111011 6
1>
1$
#235000
0$
#240000
b111101100 8
b111101100 9
b111101100 3
b1 5
b11110110 7
1$
#245000
0$
#250000
b1111011000 8
b1111011000 9
b1111011000 3
b10 5
b111101100 7
1$
#255000
0$
#260000
b11110110000 8
b11110110000 9
b11110110000 3
b11 5
b1111011000 7
1$
#265000
0$
#270000
b111101100000 8
b111101100000 9
b111101100000 3
b100 5
b11110110000 7
1$
#275000
0$
#280000
b1111011000000 8
b1111011000000 9
b1111011000000 3
b101 5
b111101100000 7
1$
#285000
0$
#290000
b11110110000000 8
b11110110000000 9
b11110110000000 3
b110 5
b1111011000000 7
1$
#295000
0$
#300000
b111101100000000 8
b111101100000000 9
b111101100000000 3
b111 5
b11110110000000 7
1$
#305000
0$
#310000
b1111011000000000 8
b1111011000000000 9
b1111011000000000 3
b1000 5
b111101100000000 7
1$
#315000
0$
#320000
b1110110000000000 8
b1 1
b11111111110000110 2
b1110110000000000 9
b1 4
b11110110000000000 3
b1001 5
b1111011000000000 7
1$
#325000
0$
#330000
b1101100000000000 8
b11 1
b11111111110001000 2
b1101100000000000 9
b11 4
b111101100000000000 3
b1010 5
b1110110000000000 7
b1 0
1$
#335000
0$
#340000
b1011000000000000 8
b111 1
b11111111110001100 2
b1011000000000000 9
b111 4
b1111011000000000000 3
b1011 5
b1101100000000000 7
b11 0
1$
#345000
0$
#350000
b110000000000000 8
b1111 1
b11111111110010100 2
b110000000000000 9
b1111 4
b11110110000000000000 3
b1100 5
b1011000000000000 7
b111 0
1$
#355000
0$
#360000
b1100000000000000 8
b11110 1
b11111111110100011 2
b1100000000000000 9
b11110 4
b111101100000000000000 3
b1101 5
b110000000000000 7
b1111 0
1$
#365000
0$
#370000
b1000000000000000 8
b111101 1
b11111111111000010 2
b1000000000000000 9
b111101 4
b1111011000000000000000 3
b1110 5
b1100000000000000 7
b11110 0
1$
#375000
0$
#380000
b1 8
b0 1
0<
b0 2
b0 9
b1111011 4
b11110110000000000000000 3
b1111 5
b1000000000000000 7
b111101 0
1$
#385000
0$
#390000
b1 #
b1 :
0?
1/
0+
1!
b10 8
1<
b11111111110000101 2
b10 9
b0 4
b10 3
1=
b10000 5
b1 7
b0 0
1$
#395000
0$
#400000
1.
0-
0=
0>
b10001 5
1$
#405000
0$
#410000
b0 5
1$
#415000
0$
#420000
1?
1,
b10 &
b10 *
b111 %
b111 )
1(
1$
#425000
0$
#430000
0(
b0 #
b0 :
b1110 8
b11111111111111110 2
b1110 9
b1110 3
0/
1+
0!
0.
1-
0,
b111 7
b10 6
1>
1$
#435000
0$
#440000
b11100 8
b11100 9
b11100 3
b1 5
b1110 7
1$
#445000
0$
#450000
b111000 8
b111000 9
b111000 3
b10 5
b11100 7
1$
#455000
0$
#460000
b1110000 8
b1110000 9
b1110000 3
b11 5
b111000 7
1$
#465000
0$
#470000
b11100000 8
b11100000 9
b11100000 3
b100 5
b1110000 7
1$
#475000
0$
#480000
b111000000 8
b111000000 9
b111000000 3
b101 5
b11100000 7
1$
#485000
0$
#490000
b1110000000 8
b1110000000 9
b1110000000 3
b110 5
b111000000 7
1$
#495000
0$
#500000
b11100000000 8
b11100000000 9
b11100000000 3
b111 5
b1110000000 7
1$
#505000
0$
#510000
b111000000000 8
b111000000000 9
b111000000000 3
b1000 5
b11100000000 7
1$
#515000
0$
#520000
b1110000000000 8
b1110000000000 9
b1110000000000 3
b1001 5
b111000000000 7
1$
#525000
0$
#530000
b11100000000000 8
b11100000000000 9
b11100000000000 3
b1010 5
b1110000000000 7
1$
#535000
0$
#540000
b111000000000000 8
b111000000000000 9
b111000000000000 3
b1011 5
b11100000000000 7
1$
#545000
0$
#550000
b1110000000000000 8
b1110000000000000 9
b1110000000000000 3
b1100 5
b111000000000000 7
1$
#555000
0$
#560000
b1100000000000000 8
b1 1
b11111111111111111 2
b1100000000000000 9
b1 4
b11100000000000000 3
b1101 5
b1110000000000000 7
1$
#565000
0$
#570000
b1000000000000001 8
0<
b1 2
b1000000000000000 9
b11 4
b111000000000000000 3
b1110 5
b1100000000000000 7
b1 0
1$
#575000
0$
#580000
b11 8
b10 9
b110000000000000010 3
b1111 5
b1000000000000001 7
1$
#585000
0$
#590000
b1 "
b1 ;
b11 #
b11 :
0?
1/
0+
1!
b111 8
b0 1
b0 2
b110 9
b10 4
b100000000000000110 3
1=
b10000 5
b11 7
1$
#595000
0$
#600000
1.
0-
0=
0>
b10001 5
1$
#605000
0$
#610000
b0 5
1$
#615000
0$
#620000
1?
1,
b101 &
b101 *
b1111111111111111 %
b1111111111111111 )
1(
1$
#625000
0$
#630000
0(
b0 "
b0 ;
b0 #
b0 :
b1111111111111110 8
b1 1
1<
b11111111111111100 2
b1111111111111110 9
b1 4
b11111111111111110 3
0/
1+
0!
0.
1-
0,
b1111111111111111 7
b101 6
b0 0
1>
1$
#635000
0$
#640000
b1111111111111100 8
b11 1
b11111111111111110 2
b1111111111111100 9
b11 4
b111111111111111100 3
b1 5
b1111111111111110 7
b1 0
1$
#645000
0$
#650000
b1111111111111001 8
b10 1
0<
b10 2
b1111111111111000 9
b111 4
b1111111111111111000 3
b10 5
b1111111111111100 7
b11 0
1$
#655000
0$
#660000
b1111111111110011 8
b0 1
b0 2
b1111111111110010 9
b101 4
b1011111111111110010 3
b11 5
b1111111111111001 7
b10 0
1$
#665000
0$
#670000
b1111111111100110 8
b1 1
1<
b11111111111111100 2
b1111111111100110 9
b1 4
b11111111111100110 3
b100 5
b1111111111110011 7
b0 0
1$
#675000
0$
#680000
b1111111111001100 8
b11 1
b11111111111111110 2
b1111111111001100 9
b11 4
b111111111111001100 3
b101 5
b1111111111100110 7
b1 0
1$
#685000
0$
#690000
b1111111110011001 8
b10 1
0<
b10 2
b1111111110011000 9
b111 4
b1111111111110011000 3
b110 5
b1111111111001100 7
b11 0
1$
#695000
0$
#700000
b1111111100110011 8
b0 1
b0 2
b1111111100110010 9
b101 4
b1011111111100110010 3
b111 5
b1111111110011001 7
b10 0
1$
#705000
0$
#710000
b1111111001100110 8
b1 1
1<
b11111111111111100 2
b1111111001100110 9
b1 4
b11111111001100110 3
b1000 5
b1111111100110011 7
b0 0
1$
#715000
0$
#720000
b1111110011001100 8
b11 1
b11111111111111110 2
b1111110011001100 9
b11 4
b111111110011001100 3
b1001 5
b1111111001100110 7
b1 0
1$
#725000
0$
#730000
b1111100110011001 8
b10 1
0<
b10 2
b1111100110011000 9
b111 4
b1111111100110011000 3
b1010 5
b1111110011001100 7
b11 0
1$
#735000
0$
#740000
b1111001100110011 8
b0 1
b0 2
b1111001100110010 9
b101 4
b1011111001100110010 3
b1011 5
b1111100110011001 7
b10 0
1$
#745000
0$
#750000
b1110011001100110 8
b1 1
1<
b11111111111111100 2
b1110011001100110 9
b1 4
b11110011001100110 3
b1100 5
b1111001100110011 7
b0 0
1$
#755000
0$
#760000
b1100110011001100 8
b11 1
b11111111111111110 2
b1100110011001100 9
b11 4
b111100110011001100 3
b1101 5
b1110011001100110 7
b1 0
1$
#765000
0$
#770000
b1001100110011001 8
b10 1
0<
b10 2
b1001100110011000 9
b111 4
b1111001100110011000 3
b1110 5
b1100110011001100 7
b11 0
1$
#775000
0$
#780000
b11001100110011 8
b0 1
b0 2
b11001100110010 9
b101 4
b1010011001100110010 3
b1111 5
b1001100110011001 7
b10 0
1$
#785000
0$
#790000
b11001100110011 #
b11001100110011 :
0?
1/
0+
1!
b110011001100110 8
1<
b11111111111111011 2
b110011001100110 9
b0 4
b110011001100110 3
1=
b10000 5
b11001100110011 7
b0 0
1$
#795000
0$
#800000
1.
0-
0=
0>
b10001 5
1$
#805000
0$
#810000
1?
1,
1(
b100110000000001 &
b100110000000001 *
b111001111010001 %
b111001111010001 )
b0 5
1$
#815000
0$
#820000
0(
0/
1+
0!
0.
1-
0,
b0 #
b0 :
b1110011110100010 8
b11011001111111111 2
b1110011110100010 9
b1110011110100010 3
1>
b111001111010001 7
b100110000000001 6
1$
#825000
0$
#830000
b1100111101000100 8
b1 1
b11011010000000000 2
b1100111101000100 9
b1 4
b11100111101000100 3
b1 5
b1110011110100010 7
1$
#835000
0$
#840000
b1001111010001000 8
b11 1
b11011010000000010 2
b1001111010001000 9
b11 4
b111001111010001000 3
b10 5
b1100111101000100 7
b1 0
1$
#845000
0$
#850000
b11110100010000 8
b111 1
b11011010000000110 2
b11110100010000 9
b111 4
b1110011110100010000 3
b11 5
b1001111010001000 7
b11 0
1$
#855000
0$
#860000
b111101000100000 8
b1110 1
b11011010000001101 2
b111101000100000 9
b1110 4
b11100111101000100000 3
b100 5
b11110100010000 7
b111 0
1$
#865000
0$
#870000
b1111010001000000 8
b11100 1
b11011010000011011 2
b1111010001000000 9
b11100 4
b111001111010001000000 3
b101 5
b111101000100000 7
b1110 0
1$
#875000
0$
#880000
b1110100010000000 8
b111001 1
b11011010000111000 2
b1110100010000000 9
b111001 4
b1110011110100010000000 3
b110 5
b1111010001000000 7
b11100 0
1$
#885000
0$
#890000
b1101000100000000 8
b1110011 1
b11011010001110010 2
b1101000100000000 9
b1110011 4
b11100111101000100000000 3
b111 5
b1110100010000000 7
b111001 0
1$
#895000
0$
#900000
b1010001000000000 8
b11100111 1
b11011010011100110 2
b1010001000000000 9
b11100111 4
b111001111010001000000000 3
b1000 5
b1101000100000000 7
b1110011 0
1$
#905000
0$
#910000
b100010000000000 8
b111001111 1
b11011010111001110 2
b100010000000000 9
b111001111 4
b1110011110100010000000000 3
b1001 5
b1010001000000000 7
b11100111 0
1$
#915000
0$
#920000
b1000100000000000 8
b1110011110 1
b11011011110011101 2
b1000100000000000 9
b1110011110 4
b11100111101000100000000000 3
b1010 5
b100010000000000 7
b111001111 0
1$
#925000
0$
#930000
b1000000000000 8
b11100111101 1
b11011101100111100 2
b1000000000000 9
b11100111101 4
b111001111010001000000000000 3
b1011 5
b1000100000000000 7
b1110011110 0
1$
#935000
0$
#940000
b10000000000000 8
b111001111010 1
b11100001001111001 2
b10000000000000 9
b111001111010 4
b1110011110100010000000000000 3
b1100 5
b1000000000000 7
b11100111101 0
1$
#945000
0$
#950000
b100000000000000 8
b1110011110100 1
b11101000011110011 2
b100000000000000 9
b1110011110100 4
b11100111101000100000000000000 3
b1101 5
b10000000000000 7
b111001111010 0
1$
#955000
0$
#960000
b1000000000000000 8
b11100111101000 1
b11110110111100111 2
b1000000000000000 9
b11100111101000 4
b111001111010001000000000000000 3
b1110 5
b100000000000000 7
b1110011110100 0
1$
#965000
0$
#970000
b1 8
b10011111010000 1
0<
b10011111010000 2
b0 9
b111001111010001 4
b1110011110100010000000000000000 3
b1111 5
b1000000000000000 7
b11100111101000 0
1$
#975000
0$
#980000
b10011111010000 "
b10011111010000 ;
b1 #
b1 :
0?
1/
0+
1!
b11 8
b1110011111 1
b1110011111 2
b10 9
b100111110100000 4
b1001111101000000000000000000010 3
1=
b10000 5
b1 7
b10011111010000 0
1$
#985000
0$
#990000
0=
1.
0-
b10001 5
0>
1$
#995000
0$
#1000000
1?
1,
1(
b1001101010001110 &
b1001101010001110 *
b1010011110100111 %
b1010011110100111 )
b0 5
1$
#1005000
0$
#1010000
0(
b0 "
b0 ;
b0 #
b0 :
b100111101001110 8
b1 1
1<
b10110010101110011 2
b100111101001110 9
b1 4
b10100111101001110 3
0/
1+
0!
0.
1-
0,
b1010011110100111 7
b1001101010001110 6
b0 0
1>
1$
#1015000
0$
#1020000
b1001111010011100 8
b10 1
b10110010101110100 2
b1001111010011100 9
b10 4
b101001111010011100 3
b1 5
b100111101001110 7
b1 0
1$
#1025000
0$
#1030000
b11110100111000 8
b101 1
b10110010101110111 2
b11110100111000 9
b101 4
b1010011110100111000 3
b10 5
b1001111010011100 7
b10 0
1$
#1035000
0$
#1040000
b111101001110000 8
b1010 1
b10110010101111100 2
b111101001110000 9
b1010 4
b10100111101001110000 3
b11 5
b11110100111000 7
b101 0
1$
#1045000
0$
#1050000
b1111010011100000 8
b10100 1
b10110010110000110 2
b1111010011100000 9
b10100 4
b101001111010011100000 3
b100 5
b111101001110000 7
b1010 0
1$
#1055000
0$
#1060000
b1110100111000000 8
b101001 1
b10110010110011011 2
b1110100111000000 9
b101001 4
b1010011110100111000000 3
b101 5
b1111010011100000 7
b10100 0
1$
#1065000
0$
#1070000
b1101001110000000 8
b1010011 1
b10110010111000101 2
b1101001110000000 9
b1010011 4
b10100111101001110000000 3
b110 5
b1110100111000000 7
b101001 0
1$
#1075000
0$
#1080000
b1010011100000000 8
b10100111 1
b10110011000011001 2
b1010011100000000 9
b10100111 4
b101001111010011100000000 3
b111 5
b1101001110000000 7
b1010011 0
1$
#1085000
0$
#1090000
b100111000000000 8
b101001111 1
b10110011011000001 2
b100111000000000 9
b101001111 4
b1010011110100111000000000 3
b1000 5
b1010011100000000 7
b10100111 0
1$
#1095000
0$
#1100000
b1001110000000000 8
b1010011110 1
b10110100000010000 2
b1001110000000000 9
b1010011110 4
b10100111101001110000000000 3
b1001 5
b100111000000000 7
b101001111 0
1$
#1105000
0$
#1110000
b11100000000000 8
b10100111101 1
b10110101010101111 2
b11100000000000 9
b10100111101 4
b101001111010011100000000000 3
b1010 5
b1001110000000000 7
b1010011110 0
1$
#1115000
0$
#1120000
b111000000000000 8
b101001111010 1
b10110111111101100 2
b111000000000000 9
b101001111010 4
b1010011110100111000000000000 3
b1011 5
b11100000000000 7
b10100111101 0
1$
#1125000
0$
#1130000
b1110000000000000 8
b1010011110100 1
b10111101001100110 2
b1110000000000000 9
b1010011110100 4
b10100111101001110000000000000 3
b1100 5
b111000000000000 7
b101001111010 0
1$
#1135000
0$
#1140000
b1100000000000000 8
b10100111101001 1
b11000111101011011 2
b1100000000000000 9
b10100111101001 4
b101001111010011100000000000000 3
b1101 5
b1110000000000000 7
b1010011110100 0
1$
#1145000
0$
#1150000
b1000000000000000 8
b101001111010011 1
b11011100101000101 2
b1000000000000000 9
b101001111010011 4
b1010011110100111000000000000000 3
b1110 5
b1100000000000000 7
b10100111101001 0
1$
#1155000
0$
#1160000
b1 8
b110100011001 1
0<
b110100011001 2
b0 9
b1010011110100111 4
b10100111101001110000000000000000 3
b1111 5
b1000000000000000 7
b101001111010011 0
1$
#1165000
0$
#1170000
b110100011001 "
b110100011001 ;
b1 #
b1 :
0?
1/
0+
1!
b10 8
b1101000110010 1
1<
b10111111110100100 2
b10 9
b1101000110010 4
b11010001100100000000000000010 3
1=
b10000 5
b1 7
b110100011001 0
1$
#1175000
0$
#1180000
1.
0-
0=
0>
b10001 5
1$
#1185000
0$
#1190000
1?
1,
1(
b110011100001 &
b110011100001 *
b110001000001100 %
b110001000001100 )
b0 5
1$
#1195000
0$
#1200000
0(
0/
1+
0!
0.
1-
0,
b0 "
b0 ;
b0 #
b0 :
b1100010000011000 8
b0 1
b11111001100011111 2
b1100010000011000 9
b0 4
b1100010000011000 3
1>
b110001000001100 7
b110011100001 6
b0 0
1$
#1205000
0$
#1210000
b1000100000110000 8
b1 1
b11111001100100000 2
b1000100000110000 9
b1 4
b11000100000110000 3
b1 5
b1100010000011000 7
1$
#1215000
0$
#1220000
b1000001100000 8
b11 1
b11111001100100010 2
b1000001100000 9
b11 4
b110001000001100000 3
b10 5
b1000100000110000 7
b1 0
1$
#1225000
0$
#1230000
b10000011000000 8
b110 1
b11111001100100101 2
b10000011000000 9
b110 4
b1100010000011000000 3
b11 5
b1000001100000 7
b11 0
1$
#1235000
0$
#1240000
b100000110000000 8
b1100 1
b11111001100101011 2
b100000110000000 9
b1100 4
b11000100000110000000 3
b100 5
b10000011000000 7
b110 0
1$
#1245000
0$
#1250000
b1000001100000000 8
b11000 1
b11111001100110111 2
b1000001100000000 9
b11000 4
b110001000001100000000 3
b101 5
b100000110000000 7
b1100 0
1$
#1255000
0$
#1260000
b11000000000 8
b110001 1
b11111001101010000 2
b11000000000 9
b110001 4
b1100010000011000000000 3
b110 5
b1000001100000000 7
b11000 0
1$
#1265000
0$
#1270000
b110000000000 8
b1100010 1
b11111001110000001 2
b110000000000 9
b1100010 4
b11000100000110000000000 3
b111 5
b11000000000 7
b110001 0
1$
#1275000
0$
#1280000
b1100000000000 8
b11000100 1
b11111001111100011 2
b1100000000000 9
b11000100 4
b110001000001100000000000 3
b1000 5
b110000000000 7
b1100010 0
1$
#1285000
0$
#1290000
b11000000000000 8
b110001000 1
b11111010010100111 2
b11000000000000 9
b110001000 4
b1100010000011000000000000 3
b1001 5
b1100000000000 7
b11000100 0
1$
#1295000
0$
#1300000
b110000000000000 8
b1100010000 1
b11111011000101111 2
b110000000000000 9
b1100010000 4
b11000100000110000000000000 3
b1010 5
b11000000000000 7
b110001000 0
1$
#1305000
0$
#1310000
b1100000000000000 8
b11000100000 1
b11111100100111111 2
b1100000000000000 9
b11000100000 4
b110001000001100000000000000 3
b1011 5
b110000000000000 7
b1100010000 0
1$
#1315000
0$
#1320000
b1000000000000000 8
b110001000001 1
b11111111101100000 2
b1000000000000000 9
b110001000001 4
b1100010000011000000000000000 3
b1100 5
b1100000000000000 7
b11000100000 0
1$
#1325000
0$
#1330000
b1 8
b101110100010 1
0<
b101110100010 2
b0 9
b1100010000011 4
b11000100000110000000000000000 3
b1101 5
b1000000000000000 7
b110001000001 0
1$
#1335000
0$
#1340000
b11 8
b101001100011 1
b101001100011 2
b10 9
b1011101000100 4
b10111010001000000000000000010 3
b1110 5
b1 7
b101110100010 0
1$
#1345000
0$
#1350000
b111 8
b11111100101 1
b11111100101 2
b110 9
b1010011000110 4
b10100110001100000000000000110 3
b1111 5
b11 7
b101001100011 0
1$
#1355000
0$
#1360000
b11111100101 "
b11111100101 ;
b111 #
b111 :
0?
1/
0+
1!
b1111 8
b1011101001 1
b1011101001 2
b1110 9
b111111001010 4
b1111110010100000000000001110 3
1=
b10000 5
b111 7
b11111100101 0
1$
#1365000
0$
#1370000
0=
1.
0-
b10001 5
0>
1$
#1375000
0$
#1380000
1?
1,
1(
b1111010001110100 &
b1111010001110100 *
b1111001110001110 %
b1111001110001110 )
b0 5
1$
#1385000
0$
#1390000
0(
b0 "
b0 ;
b0 #
b0 :
b1110011100011100 8
b1 1
1<
b10000101110001101 2
b1110011100011100 9
b1 4
b11110011100011100 3
0/
1+
0!
0.
1-
0,
b1111001110001110 7
b1111010001110100 6
b0 0
1>
1$
#1395000
0$
#1400000
b1100111000111000 8
b11 1
b10000101110001111 2
b1100111000111000 9
b11 4
b111100111000111000 3
b1 5
b1110011100011100 7
b1 0
1$
#1405000
0$
#1410000
b1001110001110000 8
b111 1
b10000101110010011 2
b1001110001110000 9
b111 4
b1111001110001110000 3
b10 5
b1100111000111000 7
b11 0
1$
#1415000
0$
#1420000
b11100011100000 8
b1111 1
b10000101110011011 2
b11100011100000 9
b1111 4
b11110011100011100000 3
b11 5
b1001110001110000 7
b111 0
1$
#1425000
0$
#1430000
b111000111000000 8
b11110 1
b10000101110101010 2
b111000111000000 9
b11110 4
b111100111000111000000 3
b100 5
b11100011100000 7
b1111 0
1$
#1435000
0$
#1440000
b1110001110000000 8
b111100 1
b10000101111001000 2
b1110001110000000 9
b111100 4
b1111001110001110000000 3
b101 5
b111000111000000 7
b11110 0
1$
#1445000
0$
#1450000
b1100011100000000 8
b1111001 1
b10000110000000101 2
b1100011100000000 9
b1111001 4
b11110011100011100000000 3
b110 5
b1110001110000000 7
b111100 0
1$
#1455000
0$
#1460000
b1000111000000000 8
b11110011 1
b10000110001111111 2
b1000111000000000 9
b11110011 4
b111100111000111000000000 3
b111 5
b1100011100000000 7
b1111001 0
1$
#1465000
0$
#1470000
b1110000000000 8
b111100111 1
b10000110101110011 2
b1110000000000 9
b111100111 4
b1111001110001110000000000 3
b1000 5
b1000111000000000 7
b11110011 0
1$
#1475000
0$
#1480000
b11100000000000 8
b1111001110 1
b10000111101011010 2
b11100000000000 9
b1111001110 4
b11110011100011100000000000 3
b1001 5
b1110000000000 7
b111100111 0
1$
#1485000
0$
#1490000
b111000000000000 8
b11110011100 1
b10001001100101000 2
b111000000000000 9
b11110011100 4
b111100111000111000000000000 3
b1010 5
b11100000000000 7
b1111001110 0
1$
#1495000
0$
#1500000
b1110000000000000 8
b111100111000 1
b10001101011000100 2
b1110000000000000 9
b111100111000 4
b1111001110001110000000000000 3
b1011 5
b111000000000000 7
b11110011100 0
1$
#1505000
0$
#1510000
b1100000000000000 8
b1111001110001 1
b10010100111111101 2
b1100000000000000 9
b1111001110001 4
b11110011100011100000000000000 3
b1100 5
b1110000000000000 7
b111100111000 0
1$
#1515000
0$
#1520000
b1000000000000000 8
b11110011100011 1
b10100100001101111 2
b1000000000000000 9
b11110011100011 4
b111100111000111000000000000000 3
b1101 5
b1100000000000000 7
b1111001110001 0
1$
#1525000
0$
#1530000
b0 8
b111100111000111 1
b11000010101010011 2
b0 9
b111100111000111 4
b1111001110001110000000000000000 3
b1110 5
b1000000000000000 7
b11110011100011 0
1$
#1535000
0$
#1540000
b1111001110001110 1
b11111111100011010 2
b1111001110001110 4
b11110011100011100000000000000000 3
b1111 5
b0 7
b111100111000111 0
1$
#1545000
0$
#1550000
b1111001110001110 "
b1111001110001110 ;
0?
1/
0+
1!
b1 8
b1111001010101000 1
0<
b1111001010101000 2
b11110011100011100 4
b111100111000111000000000000000000 3
1=
b10000 5
b1111001110001110 0
1$
#1555000
0$
#1560000
1.
0-
0=
0>
b10001 5
1$
#1565000
0$
#1570000
1?
1,
1(
b1110111001001101 &
b1110111001001101 *
b1010100001010100 %
b1010100001010100 )
b0 5
1$
#1575000
0$
#1580000
0(
0/
1+
0!
0.
1-
0,
b0 "
b0 ;
b0 #
b0 :
b101000010101000 8
b1 1
1<
b10001000110110100 2
b101000010101000 9
b1 4
b10101000010101000 3
1>
b1010100001010100 7
b1110111001001101 6
b0 0
1$
#1585000
0$
#1590000
b1010000101010000 8
b10 1
b10001000110110101 2
b1010000101010000 9
b10 4
b101010000101010000 3
b1 5
b101000010101000 7
b1 0
1$
#1595000
0$
#1600000
b100001010100000 8
b101 1
b10001000110111000 2
b100001010100000 9
b101 4
b1010100001010100000 3
b10 5
b1010000101010000 7
b10 0
1$
#1605000
0$
#1610000
b1000010101000000 8
b1010 1
b10001000110111101 2
b1000010101000000 9
b1010 4
b10101000010101000000 3
b11 5
b100001010100000 7
b101 0
1$
#1615000
0$
#1620000
b101010000000 8
b10101 1
b10001000111001000 2
b101010000000 9
b10101 4
b101010000101010000000 3
b100 5
b1000010101000000 7
b1010 0
1$
#1625000
0$
#1630000
b1010100000000 8
b101010 1
b10001000111011101 2
b1010100000000 9
b101010 4
b1010100001010100000000 3
b101 5
b101010000000 7
b10101 0
1$
#1635000
0$
#1640000
b10101000000000 8
b1010100 1
b10001001000000111 2
b10101000000000 9
b1010100 4
b10101000010101000000000 3
b110 5
b1010100000000 7
b101010 0
1$
#1645000
0$
